twitch_to_clip/__init__.py
twitch_to_clip/__main__.py
twitch_to_clip/create_short.py
twitch_to_clip/dl_and_create.py
twitch_to_clip/dl_twitch.py
twitch_to_clip/ffmpeg_funcs.py
twitch_to_clip-1.0.3.dist-info/entry_points.txt
twitch_to_clip-1.0.3.dist-info/LICENSE
twitch_to_clip-1.0.3.dist-info/WHEEL
twitch_to_clip-1.0.3.dist-info/METADATA
twitch_to_clip-1.0.3.dist-info/RECORD
