Metadata-Version: 2.1
Name: twitch-to-clip
Version: 1.0.3
Summary: Create vertical videos from twitch clips
Author-email: Emmanuil Borovikovs <eb.dev.99@gmail.com>
Requires-Python: >=3.7
Classifier: License :: OSI Approved :: GNU General Public License v3 (GPLv3)
Requires-Dist: twitch-dl>=2.*
Project-URL: repository, https://github.com/EB1811/twitch-to-clip
